bmkgdashboard/__init__.py
bmkgdashboard-0.8.dist-info/LICENSE
bmkgdashboard-0.8.dist-info/METADATA
bmkgdashboard-0.8.dist-info/WHEEL
bmkgdashboard-0.8.dist-info/top_level.txt
bmkgdashboard-0.8.dist-info/RECORD
