Metadata-Version: 2.1
Name: bmkgdashboard
Version: 0.8
Summary: this package is src for BMKG indonesian earthquake live and last articlee
Home-page: https://github.com/sencho-masteringpy/bmkg-dashboard
Author: Sencho Parameswara
Author-email: senchoparameswara@gmail.com
License: UNKNOWN
Project-URL: MyWeb, https://senchooo.com
Platform: UNKNOWN
Classifier: Programming Language :: Python :: 3
Classifier: License :: OSI Approved :: GNU Lesser General Public License v3 (LGPLv3)
Classifier: Operating System :: OS Independent
Classifier: Development Status :: 4 - Beta
Requires-Python: >=3.6
License-File: LICENSE
